{
	"name": "pipeline6",
	"properties": {
		"activities": [
			{
				"name": "Get MetadataSRC",
				"type": "GetMetadata",
				"dependsOn": [],
				"policy": {
					"timeout": "0.12:00:00",
					"retry": 0,
					"retryIntervalInSeconds": 30,
					"secureOutput": false,
					"secureInput": false
				},
				"userProperties": [],
				"typeProperties": {
					"dataset": {
						"referenceName": "ds_param_folder",
						"type": "DatasetReference",
						"parameters": {
							"folder": "triggerdata",
							"container": "source"
						}
					},
					"fieldList": [
						"childItems"
					],
					"storeSettings": {
						"type": "AzureBlobFSReadSettings",
						"recursive": true,
						"enablePartitionDiscovery": false
					},
					"formatSettings": {
						"type": "DelimitedTextReadSettings"
					}
				}
			},
			{
				"name": "Get MetadataSINK",
				"type": "GetMetadata",
				"dependsOn": [],
				"policy": {
					"timeout": "0.12:00:00",
					"retry": 0,
					"retryIntervalInSeconds": 30,
					"secureOutput": false,
					"secureInput": false
				},
				"userProperties": [],
				"typeProperties": {
					"dataset": {
						"referenceName": "ds_param_folder",
						"type": "DatasetReference",
						"parameters": {
							"folder": "files",
							"container": "destination"
						}
					},
					"fieldList": [
						"childItems"
					],
					"storeSettings": {
						"type": "AzureBlobFSReadSettings",
						"recursive": true,
						"enablePartitionDiscovery": false
					},
					"formatSettings": {
						"type": "DelimitedTextReadSettings"
					}
				}
			},
			{
				"name": "ForEach1",
				"type": "ForEach",
				"dependsOn": [
					{
						"activity": "Get MetadataSRC",
						"dependencyConditions": [
							"Succeeded"
						]
					},
					{
						"activity": "ForEach2",
						"dependencyConditions": [
							"Succeeded"
						]
					}
				],
				"userProperties": [],
				"typeProperties": {
					"items": {
						"value": "@activity('Get MetadataSRC').output.childItems",
						"type": "Expression"
					},
					"activities": [
						{
							"name": "If Condition1",
							"type": "IfCondition",
							"dependsOn": [],
							"userProperties": [],
							"typeProperties": {
								"expression": {
									"value": "@contains(variables('sink_file'),item().name)",
									"type": "Expression"
								},
								"ifFalseActivities": [
									{
										"name": "Copy data1",
										"type": "Copy",
										"dependsOn": [],
										"policy": {
											"timeout": "0.12:00:00",
											"retry": 0,
											"retryIntervalInSeconds": 30,
											"secureOutput": false,
											"secureInput": false
										},
										"userProperties": [],
										"typeProperties": {
											"source": {
												"type": "DelimitedTextSource",
												"storeSettings": {
													"type": "AzureBlobFSReadSettings",
													"recursive": true,
													"enablePartitionDiscovery": false
												},
												"formatSettings": {
													"type": "DelimitedTextReadSettings"
												}
											},
											"sink": {
												"type": "DelimitedTextSink",
												"storeSettings": {
													"type": "AzureBlobFSWriteSettings"
												},
												"formatSettings": {
													"type": "DelimitedTextWriteSettings",
													"quoteAllText": true,
													"fileExtension": ".txt"
												}
											},
											"enableStaging": false,
											"translator": {
												"type": "TabularTranslator",
												"typeConversion": true,
												"typeConversionSettings": {
													"allowDataTruncation": true,
													"treatBooleanAsNumber": false
												}
											}
										},
										"inputs": [
											{
												"referenceName": "ds_parameterized_csv",
												"type": "DatasetReference",
												"parameters": {
													"p_folder": "tiggerdata",
													"p_file": {
														"value": "@item().name\n",
														"type": "Expression"
													},
													"p_container": "source"
												}
											}
										],
										"outputs": [
											{
												"referenceName": "ds_parameterized",
												"type": "DatasetReference",
												"parameters": {
													"p_folder": "files",
													"p_file": {
														"value": "@item().name",
														"type": "Expression"
													}
												}
											}
										]
									}
								],
								"ifTrueActivities": [
									{
										"name": "Wait1",
										"type": "Wait",
										"dependsOn": [],
										"userProperties": [],
										"typeProperties": {
											"waitTimeInSeconds": 1
										}
									}
								]
							}
						}
					]
				}
			},
			{
				"name": "ForEach2",
				"type": "ForEach",
				"dependsOn": [
					{
						"activity": "Get MetadataSINK",
						"dependencyConditions": [
							"Succeeded"
						]
					}
				],
				"userProperties": [],
				"typeProperties": {
					"items": {
						"value": "@activity('Get MetadataSINK').output.childItems",
						"type": "Expression"
					},
					"activities": [
						{
							"name": "Append variable1",
							"type": "AppendVariable",
							"dependsOn": [],
							"userProperties": [],
							"typeProperties": {
								"variableName": "sink_file",
								"value": {
									"value": "@item().name",
									"type": "Expression"
								}
							}
						}
					]
				}
			}
		],
		"variables": {
			"sink_file": {
				"type": "Array"
			}
		},
		"annotations": [],
		"lastPublishTime": "2025-06-13T09:14:09Z"
	},
	"type": "Microsoft.DataFactory/factories/pipelines"
}